{"iodomethylzinc": 3, "idodide": 1, "is": 94, "the": 1332, "active": 2, "reagent": 1, "in": 359, "simmons-smith": 1, "reaction": 3, "for": 142, "example": 5, "iodide": 4, "formed": 2, "situ": 1, "from": 100, "diiodomethane": 1, "and": 500, "a": 527, "zinc-copper": 1, "couple": 16, "reacts": 1, "with": 122, "cyclohexene": 1, "to": 445, "give": 7, "norcarane": 1, "may": 25, "also": 14, "be": 80, "generated": 1, "by": 56, "of": 432, "diazomethane": 1, "zinc": 1, "or": 79, "methylene": 1, "diethylzinc": 1, "forum": 1, "qualitative": 2, "social": 7, "research": 3, "triannual": 1, "peer-reviewed": 1, "online": 2, "academic": 2, "journal": 4, "covering": 2, "theory": 1, "methodology": 1, "application": 1, "editor-in-chief": 1, "has": 28, "been": 35, "katja": 1, "mruck": 1, "(free": 1, "university": 3, "berlin)": 1, "since": 6, "journal\u2019s": 1, "conception": 1, "articles": 4, "published": 1, "are": 56, "english": 2, "german": 2, "spanish": 2, "incorporates": 1, "internet-specific": 1, "forms": 1, "publication": 2, "such": 9, "as": 116, "video": 4, "sound": 9, "recordings": 1, "abstract": 1, "indexed": 1, "intute": 1, "sociosite": 1, "csa": 2, "sociological": 1, "abstracts": 2, "worldwide": 1, "political": 1, "science": 5, "international": 1, "bibliography": 2, "sciences": 1, "psyndex": 1, "solis": 1, "socindex": 1, "was": 225, "established": 1, "1999": 1, "it": 147, "developed": 1, "into": 56, "an": 60, "information": 3, "communication": 1, "networking": 1, "portal": 1, "project": 1, "initially": 2, "funded": 1, "you": 96, "should": 14, "read": 16, "random": 2, "start": 1, "at": 105, "this": 51, "one": 73, "i\u2019ve": 2, "talked": 2, "about": 45, "my": 15, "reading": 11, "habits": 2, "already": 8, "everyone": 4, "daily": 4, "list": 7, "reddit": 1, "hacker": 1, "news": 1, "medium": 2, "other": 27, "i": 57, "observed": 2, "behavior": 2, "than": 17, "realized": 2, "few": 17, "things:": 1, "too": 9, "picky": 1, "what": 37, "even": 28, "taking": 4, "look": 18, "essentially": 1, "mind": 9, "conditioned": 1, "100%": 1, "time": 25, "when": 56, "wasn\u2019t": 1, "actually": 8, "there": 50, "basically": 1, "skimming": 1, "through": 45, "going": 13, "directly": 3, "title": 3, "comments": 2, "without": 11, "paying": 2, "much": 9, "attention": 3, "today": 7, "decided": 4, "do": 22, "exact": 1, "opposite": 1, "took": 15, "which": 23, "course": 3, "consists": 1, "only": 27, "topics": 1, "i\u2019m": 3, "interested": 2, "just": 27, "order": 4, "them": 59, "looking": 13, "up": 55, "things": 13, "didn\u2019t": 4, "know": 14, "result": 1, "obvious": 1, "there\u2019s": 6, "so": 26, "more": 20, "learn": 2, "you\u2019re": 7, "not": 88, "constrained": 1, "your": 26, "brain": 3, "finds": 2, "interesting": 4, "congratulations": 1, "you\u2019ve": 4, "taken": 6, "first": 24, "step": 3, "bringing": 1, "everything": 5, "bizarre": 1, "beautiful": 10, "over": 47, "three": 14, "years": 19, "now\u2013and": 1, "often": 12, "writing": 3, "length": 3, "some": 29, "our": 10, "fascinating": 1, "findings": 1, "all": 63, "while": 17, "case": 5, "missed": 2, "here\u2019s": 2, "quick": 1, "way": 32, "catch": 2, "further": 5, "ado": 2, "here": 7, "best": 3, "that": 160, "haven\u2019t": 2, "yet:": 1, "viewing": 1, "note:": 1, "clicking": 1, "on": 131, "post": 2, "image": 1, "will": 20, "open": 8, "new": 14, "window": 14, "article": 3, "internet": 1, "surfing": 1, "can": 18, "serve": 1, "many": 16, "purposes": 1, "ranging": 2, "informing": 1, "yourself": 1, "current": 1, "events": 4, "stalking": 1, "ex": 1, "scouring": 1, "portuguese": 1, "dish": 1, "make": 14, "pretentious": 1, "dinner": 5, "party": 5, "each": 27, "these": 12, "activities": 1, "united": 1, "thing": 4, "though:": 1, "absolutely": 1, "alone": 5, "but": 81, "if": 57, "cyber": 1, "solitude": 1, "isn\u2019t": 2, "enough": 9, "get": 25, "introvert": 1, "might": 19, "peruse": 1, "world\u2019s": 2, "most": 19, "remote": 1, "places": 6, "jet": 1, "off": 21, "uninhabited": 1, "archipelago": 1, "smack": 1, "between": 17, "south": 7, "africa": 1, "america": 1, "scenic": 1, "roadless": 1, "province": 1, "tibet": 1, "very": 9, "least": 5, "daydream": 1, "anything": 5, "like": 70, "us": 5, "enjoyment": 1, "nature": 3, "translated": 1, "\u201cadmiring": 1, "its": 33, "beauty": 4, "insect-free": 1, "comforts": 1, "computer": 1, "screen\u201d": 1, "rings": 1, "especially": 6, "true": 6, "natural": 4, "phenomena": 2, "they\u2019re": 9, "found": 7, "prohibitively": 1, "far": 9, "distance": 2, "home": 21, "potentially": 1, "quite": 4, "dangerous": 1, "those": 16, "naturalist\u2019s": 1, "heart": 7, "agoraphobic\u2019s": 1, "check": 4, "out": 73, "mind-blowing": 1, "twister": 1, "introduced": 1, "referred": 1, "sex": 7, "box": 6, "otters": 1, "sleep": 11, "holding": 4, "hands": 16, "twenty": 13, "percent": 1, "coffee": 4, "mugs": 1, "contain": 2, "fecal": 1, "matter": 6, "(gross)": 1, "prowl": 1, "awesome": 1, "trivia": 1, "no": 34, "handy": 1, "facts": 1, "we\u2019ve": 3, "compiled": 1, "great": 19, "news:": 2, "got": 12, "99": 1, "\u2019em": 1, "motor": 2, "city": 7, "certainly": 2, "seen": 6, "brighter": 1, "days": 6, "declaring": 1, "bankruptcy": 1, "2011": 1, "detroit": 2, "many\u2013yet": 1, "visibly\u2013suffering": 1, "cities": 1, "wake": 5, "recession": 1, "industrial": 1, "metropolis": 1, "once": 12, "served": 1, "around": 28, "two": 28, "million": 2, "people": 28, "numbers": 1, "hang": 1, "700000": 1, "truly": 1, "dying": 4, "photos": 1, "abandoned": 1, "incredibly": 1, "sobering": 1, "retrofuturism": 10, "past's": 2, "vision": 3, "future": 7, "\u2014": 6, "it's": 5, "yesterday": 1, "thought": 11, "would": 46, "their": 64, "ideas": 2, "run": 7, "gamut": 1, "charmingly": 1, "na\u00efve": 1, "amusingly": 1, "ambitious": 1, "alarmingly": 1, "accurate": 1, "they've": 1, "inspired": 1, "movement": 3, "present": 6, "artists": 2, "designers": 2, "musicians": 1, "filmmakers": 1, "channel": 1, "technological": 3, "dreams": 13, "bygone": 2, "age": 5, "term": 1, "\"retrofuturism\"": 1, "relatively": 1, "recent": 1, "appeared": 3, "advances": 2, "70s": 1, "80s": 1, "made": 13, "enormous": 1, "strides": 1, "always": 14, "directions": 2, "inhabitants": 1, "early": 2, "20th": 2, "century": 2, "had": 90, "anticipated": 1, "past": 21, "began": 19, "quaint": 1, "implausible": 1, "nostalgic": 1, "makes": 4, "sense": 3, "genre": 2, "rose": 6, "popularity": 2, "same": 9, "dystopian": 2, "fiction": 4, "fantasy": 2, "were": 79, "garnering": 1, "renewed": 1, "interest": 2, "beginning": 2, "stranger": 2, "scarier": 2, "place": 13, "enthusiasm": 1, "emerged": 1, "sometimes": 10, "comically": 1, "rosy": 1, "predictions": 2, "previous": 2, "generations": 3, "they": 106, "retrofuturistic": 5, "illustrations": 2, "judge": 1, "yen": 1, "better": 5, "transportation": 1, "airborne": 1, "dreamed": 4, "private": 1, "helicopters": 1, "hover": 1, "cars": 2, "dirigibles": 1, "personal": 2, "spaceships": 1, "float": 1, "freely": 1, "along": 3, "suspended": 2, "highways": 1, "roads": 6, "magnetized": 1, "hoops": 1, "rise": 6, "hundreds": 1, "feet": 14, "above": 15, "ground": 5, "shimmering": 2, "glass": 6, "tubes": 1, "wind": 13, "mario": 1, "kart's": 1, "rainbow": 2, "road": 4, "space-age": 1, "underground": 1, "tunnelsdomestic": 1, "life": 11, "radically": 1, "different": 7, "lens": 1, "busy": 2, "commuters": 1, "pop": 1, "pill": 1, "tastes": 1, "chicken": 1, "pot": 1, "pie": 8, "inconvenience": 1, "having": 6, "eat": 6, "fashion": 1, "favors": 1, "tall": 2, "plastic": 3, "boots": 3, "skintight": 1, "chrome": 1, "pvc": 1, "homes": 3, "affairs": 2, "(suggesting": 1, "we've": 1, "done": 2, "away": 18, "both": 13, "privacy": 1, "bricks)": 1, "moon": 2, "conservative": 1, "projections": 1, "feature": 2, "dramatically": 1, "simplified": 1, "domestic": 1, "duties": 2, "1960s": 1, "explaining": 1, "futuristic": 2, "kitchen:": 1, "though": 11, "images": 2, "common": 7, "laughable": 1, "perspective": 2, "dreamers": 2, "right:": 1, "self-driving": 1, "close": 3, "fruition": 1, "conferencing": 1, "wrist": 3, "accessories": 1, "play": 3, "tv": 2, "shows": 3, "everyday": 1, "realities": 1, "robots": 1, "(or": 1, "automated": 1, "systems)": 1, "exist": 2, "factories": 1, "designs": 1, "googie": 1, "populuxe": 1, "doo": 1, "wop": 1, "aesthetics": 1, "leaning": 1, "heavily": 2, "popping": 1, "neon": 1, "colors": 1, "svelte": 1, "steel": 1, "curvy": 1, "geometric": 1, "shapes": 1, "possible": 1, "blend": 2, "earned": 1, "own": 14, "deeply": 2, "appropriate": 1, "name:": 1, "raygun": 1, "gothic": 1, "there's": 1, "another": 13, "side": 8, "deals": 1, "view": 3, "rather": 3, "present's": 1, "writers": 1, "reimagine": 1, "creating": 2, "strange": 5, "never": 19, "happened": 2, "famous": 2, "kind": 5, "steampunk": 1, "art": 4, "gifts": 1, "old": 20, "technologies": 1, "(often": 1, "steam": 3, "power)": 1, "modern": 3, "near-modern": 1, "capabilities": 1, "historical": 2, "setting": 2, "typically": 1, "victorian": 1, "era": 1, "2004": 1, "cult": 2, "classic": 3, "sky": 8, "captain": 1, "world": 12, "tomorrow": 3, "strong": 2, "big": 5, "screen": 1, "movie": 6, "sets": 2, "robot": 1, "invasion": 1, "1939": 1, "york": 2, "intrepid": 1, "reporter": 2, "(gwyneth": 1, "paltrow)": 1, "fighter": 1, "pilot": 1, "(jude": 1, "law)": 1, "defeat": 1, "evil": 1, "scientist": 1, "doomsday": 1, "device": 1, "noted": 3, "blindingly": 1, "optimistic": 1, "nostalgia": 1, "theme": 1, "stories": 9, "confront": 1, "set": 6, "particularly": 2, "bleak": 1, "period": 1, "terry": 1, "gilliam's": 1, "1985": 1, "brazil": 1, "paints": 1, "satirical": 1, "picture": 2, "consumer-driven": 1, "dystopia": 1, "where": 23, "ineffective": 1, "machines": 1, "mind-numbingly": 1, "dull": 1, "existence": 1, "under": 19, "rule": 1, "1984-style": 1, "totalitarian": 1, "government": 2, "decades": 2, "have": 48, "confined": 1, "classics": 1, "themes": 1, "iconic": 1, "looks": 7, "becoming": 2, "increasingly": 1, "mainstream": 1, "incredibles": 1, "director": 2, "brad": 1, "bird": 3, "cited": 1, "his": 184, "influences": 1, "hard": 5, "see": 27, "retro": 2, "sensibilities": 1, "pixar": 1, "games": 1, "notably": 1, "popular": 3, "bioshock": 1, "series": 4, "influenced": 1, "according": 8, "designer": 1, "ken": 1, "levine": 1, "part": 7, "works": 4, "george": 1, "orwell's": 1, "1984": 1, "wonder": 2, "think": 7, "back": 43, "visions": 5, "want": 11, "ages": 1, "erotic": 1, "proves": 1, "then": 39, "disturbing": 1, "depressingly": 1, "racist": 1, "ads": 1, "actual": 1, "story": 8, "conjuring": 6, "namely": 1, "perron": 6, "family": 21, "enfield": 4, "haunting": 4, "movies": 3, "themselves": 7, "released": 3, "2013": 1, "met": 6, "critical": 1, "acclaim": 1, "critics": 1, "everywhere": 2, "praised": 1, "all-too-realistic": 1, "portrayal": 1, "demonic": 2, "innocent": 1, "rhode": 2, "island": 3, "viewers": 1, "assumed": 1, "nothing": 10, "wild": 6, "imaginings": 1, "james": 1, "wan": 1, "however": 12, "rooted": 2, "horrifying": 1, "experience": 2, "ed": 9, "lorraine": 7, "warren": 4, "war": 1, "2": 1, "veteran": 1, "former": 2, "police": 2, "officer": 2, "who": 31, "became": 3, "self-professed": 1, "demonologist": 1, "after": 30, "studying": 1, "subject": 1, "wife": 37, "claimed": 2, "clairvoyant": 1, "capable": 2, "communicating": 1, "demons": 2, "discovered": 4, "1952": 1, "founded": 1, "england": 3, "society": 5, "psychic": 2, "oldest": 2, "ghost": 1, "hunting": 7, "group": 2, "quickly": 2, "gained": 1, "notoriety": 1, "respected": 1, "paranormal": 2, "investigators": 2, "initial": 1, "investigation": 1, "amityville": 2, "hauntings": 3, "cases": 2, "popularized": 1, "franchise": 1, "focuses": 2, "lorraine\u2019s": 1, "experiences": 2, "exercising": 1, "possessed": 2, "families": 6, "seem": 8, "over-dramatized": 1, "impossible": 1, "believe": 6, "warrens": 5, "maintain": 1, "depicted": 2, "transpired": 1, "died": 5, "2006": 1, "consultant": 1, "film": 3, "claims": 4, "she": 249, "let": 7, "directors": 1, "take": 13, "any": 9, "dramatic": 1, "license": 1, "necessary": 1, "begins": 1, "january": 2, "1971": 1, "moved": 6, "14-room": 1, "farmhouse": 1, "harrisville": 2, "carolyn": 4, "roger": 3, "five": 5, "daughters": 4, "notice": 3, "happening": 1, "almost": 3, "immediately": 3, "started": 4, "small": 6, "broom": 1, "went": 11, "missing": 1, "seemed": 9, "move": 5, "hear": 8, "something": 18, "scraping": 1, "against": 21, "kettle": 1, "kitchen": 4, "she\u2019d": 2, "find": 4, "piles": 1, "dirt": 1, "center": 4, "newly-cleaned": 1, "floor": 10, "girls": 6, "spirits": 5, "house": 13, "harmless": 1, "angry": 1, "allegedly": 1, "researched": 1, "history": 4, "eight": 5, "mysterious": 2, "horrible": 1, "circumstances": 2, "several": 2, "children": 11, "drowned": 1, "nearby": 2, "creek": 2, "murdered": 1, "hanged": 1, "attic": 1, "spirit": 3, "bathsheba": 2, "worst": 4, "\u201cwhoever": 1, "perceived": 1, "herself": 4, "mistress": 1, "resented": 1, "competition": 1, "mother": 10, "posed": 1, "position\u201d": 1, "said": 45, "andrea": 5, "turns": 3, "real": 4, "person": 1, "named": 3, "sherman": 1, "lived": 7, "perrons": 2, "property": 2, "mid-1800s": 1, "rumored": 1, "satanist": 1, "evidence": 6, "involved": 3, "death": 11, "neighbor\u2019s": 1, "child": 3, "trial": 1, "ever": 9, "buried": 3, "baptist": 1, "cemetery": 1, "downtown": 3, "bathsheba\u2019s": 1, "tormenting": 1, "experienced": 2, "well": 9, "smelled": 1, "rotting": 1, "flesh": 2, "cause": 1, "beds": 1, "her": 267, "father": 5, "enter": 1, "basement": 3, "feel": 12, "\u201ccold": 1, "stinking": 2, "presence": 5, "behind": 13, "him\u201d": 1, "stayed": 3, "dirt-floored": 1, "cellar": 1, "heating": 1, "equipment": 1, "fail": 1, "mysteriously": 1, "causing": 1, "venture": 1, "down": 41, "ten": 6, "multiple": 1, "trips": 2, "investigate": 2, "point": 3, "conducted": 1, "seance": 5, "attempt": 3, "contact": 3, "possessing": 1, "during": 3, "speaking": 2, "tongues": 2, "rising": 3, "chair": 3, "secretly": 1, "witnessed": 1, "\u201ci": 7, "pass": 2, "out\u201d": 1, "\u201cmy": 2, "speak": 5, "language": 20, "voice": 13, "levitated": 1, "thrown": 4, "across": 13, "room\u201d": 1, "version": 1, "culminates": 1, "performing": 2, "exorcism": 1, "insists": 1, "husband": 13, "must": 17, "performed": 3, "catholic": 1, "priestsafter": 1, "kicked": 1, "worried": 2, "wife\u2019s": 1, "mental": 1, "stability": 2, "continued": 2, "live": 2, "due": 1, "financial": 1, "instability": 1, "until": 10, "able": 3, "1980": 1, "silenced": 1, "ceased": 1, "six": 4, "terrorized": 1, "demon": 1, "similar": 1, "august": 2, "1977": 1, "hodgson": 1, "seeing": 4, "hearing": 1, "janet": 2, "11": 1, "recalled": 1, "sitting": 2, "bed": 4, "dresser": 1, "slide": 1, "room": 9, "shared": 3, "brother": 1, "\u201cwe": 3, "shouted": 3, "\u2018mum": 1, "mum\u2019\u201d": 1, "sort": 4, "frightened": 1, "intrigued\u201d": 1, "later": 6, "knocking": 2, "coming": 9, "sorts": 1, "remembers": 2, "mom": 1, "thinking": 1, "burglars": 1, "drifters": 1, "hiding": 2, "calling": 2, "arrived": 3, "reported": 3, "witnessing": 1, "reporters": 1, "mirror": 5, "called": 8, "report": 1, "legos": 1, "marbles": 1, "flying": 1, "hot": 5, "touch": 5, "picked": 2, "clothing": 1, "folded": 3, "tabletops": 1, "leap": 2, "fly": 2, "dogs": 2, "barking": 1, "heard": 9, "empty": 4, "rooms": 1, "lights": 9, "flicker": 1, "coins": 1, "drop": 2, "thin": 4, "air": 4, "furniture": 1, "spin": 1, "tip": 1, "being": 7, "touched": 5, "day": 14, "iron": 1, "fireplace": 2, "upstairs": 1, "bedroom": 2, "ripped": 1, "wall": 2, "showed": 5, "claiming": 1, "wanting": 1, "faking": 1, "admitted": 1, "doing": 3, "occasion": 1, "believed": 1, "overlooked": 1, "skeptic": 1, "accused": 1, "\u201cexaggerating": 1, "making": 6, "incidents\u2026": 1, "transforming": 1, "\u201chaunting\u201d": 1, "\u201cdemonic": 1, "possession\u201d": 1, "differs": 1, "exorcism-like": 1, "practice": 2, "1979": 1, "abruptly": 1, "stopped": 6, "maintains": 1, "did": 21, "stop": 2, "shocking": 1, "murders": 1, "horror": 2, "robert": 1, "doll": 2, "haunted": 1, "loved": 4, "medical": 2, "texts": 2, "ancient": 9, "mesopotamia": 10, "provide": 2, "prescriptions": 1, "practices": 2, "curing": 1, "manner": 1, "ailments": 1, "wounds": 1, "diseases": 1, "malady": 1, "cure:": 1, "passionate": 1, "love": 17, "text": 2, "ashurbanipal's": 1, "library": 8, "nineveh": 1, "comes": 2, "passage:": 1, "patient": 1, "continually": 1, "clearing": 1, "throat": 6, "lost": 6, "words": 3, "talking": 4, "himself": 8, "he": 327, "laughing": 2, "reason": 2, "corners": 1, "fields": 5, "habitually": 1, "depressed": 1, "tight": 1, "pleasure": 1, "eating": 2, "drinking": 3, "endlessly": 1, "repeating": 1, "sighs": 1, "`ah": 1, "poor": 4, "heart'": 1, "\u2013": 5, "suffering": 1, "lovesickness": 1, "man": 23, "woman": 35, "marriage": 29, "vital": 1, "importance": 1, "literally": 1, "because": 9, "ensured": 1, "continuation": 2, "line": 8, "provided": 3, "arranged": 3, "marriages": 5, "norm": 1, "-": 2, "herodotus": 5, "bridal": 1, "auctions": 1, "women": 19, "sold": 4, "highest": 1, "bidder": 1, "human": 1, "relationships": 1, "complex": 1, "layered": 1, "complexity": 1, "emotion": 1, "historian": 1, "karen": 1, "nemet-nejat": 3, "notes": 2, "\u201clike": 1, "throughout": 4, "mesopotamians": 3, "fell": 11, "love\u201d": 3, "`love": 1, "songs'": 1, "attests": 1, "commonality": 1, "deep": 5, "romantic": 3, "attachment": 1, "couples": 5, "titles": 1, "poems": 8, "illustrate": 2, "this:": 1, "`sleep": 1, "begone": 1, "hold": 5, "darling": 1, "arms'": 1, "akkadian": 2, "composition": 1, "c": 1, "1750": 1, "bce": 3, "depicts": 1, "lovers": 1, "arguing": 2, "feels": 3, "attracted": 1, "convince": 1, "him": 65, "end": 8, "discussed": 2, "problem": 3, "reconciles": 1, "clear": 3, "now": 18, "happily": 1, "together": 10, "business": 4, "contrasted": 1, "sharing": 1, "lives": 4, "`business": 1, "side'": 1, "reports": 1, "every": 12, "lifetime": 2, "sit": 5, "outside": 12, "temple": 1, "ishtar": 2, "(inanna)": 1, "agree": 1, "whatever": 2, "chose": 3, "custom": 1, "ensure": 2, "fertility": 1, "prosperity": 1, "community": 2, "woman's": 2, "virginity": 1, "considered": 4, "requisite": 1, "unlikely": 1, "unmarried": 1, "yet": 4, "states": 3, "`every": 1, "woman'": 1, "required": 2, "sacred": 1, "prostitution": 1, "describes": 4, "challenged": 1, "modern-day": 3, "scholars": 1, "description": 1, "bride": 8, "auction": 2, "writes:": 4, "year": 4, "village": 1, "young": 13, "eligible": 1, "marry": 4, "collected": 1, "men": 11, "stood": 10, "circle": 4, "herald": 1, "offered": 3, "sale": 3, "high": 2, "price": 1, "ranked": 1, "next": 10, "wives": 3, "richest": 1, "babylonians": 2, "wished": 1, "wed": 1, "bid": 2, "loveliest": 1, "commoners": 1, "concerned": 2, "received": 1, "uglier": 1, "monetary": 1, "compensation\u2026all": 1, "liked": 1, "come": 19, "distant": 2, "villages": 1, "customs": 3, "fallen": 4, "disuse": 1, "mesopotamian": 3, "expectations": 1, "legal": 3, "contract": 6, "girl": 10, "(the": 2, "groom": 4, "paid": 3, "girl's": 1, "bride-price)": 2, "commonly": 3, "functioned": 1, "foundation": 3, "scholar": 2, "stephen": 1, "bertman": 5, "comments:": 1, "sumerians": 2, "word": 3, "`love'": 1, "compound": 1, "verb": 1, "literal": 1, "meant": 2, "`to": 2, "measure": 1, "earth'": 1, "mark": 3, "land'": 1, "among": 3, "(and": 1, "likely": 3, "assyrians": 1, "well)": 1, "fundamentally": 1, "arrangement": 1, "designed": 1, "assure": 1, "perpetuate": 1, "orderly": 2, "inevitable": 1, "emotional": 1, "component": 1, "prime": 1, "intent": 1, "eyes": 23, "state": 4, "companionship": 1, "procreation": 1, "happiness": 1, "communal": 1, "continuity": 1, "doubt": 2, "`official'": 1, "suggest": 1, "simply": 2, "married": 8, "(although": 2, "living": 7, "marrying)": 1, "indeed": 1, "law": 1, "stated": 1, "drawn": 4, "executed": 6, "`marries'": 1, "wife\u2026": 1, "joint": 1, "decision": 2, "negotiation": 1, "representatives": 1, "signed": 1, "witnesses": 1, "ceremony": 3, "could": 54, "planned": 1, "wedding": 3, "include": 3, "feast": 2, "legitimate": 1, "process": 2, "stages": 1, "needed": 2, "legally": 1, "married:": 1, "engagement/marriage": 1, "payment": 1, "dowry": 3, "sexual": 1, "intercourse": 2, "expected": 3, "virgin": 2, "night": 15, "become": 4, "pregnant": 2, "moving": 3, "father-in-law's": 1, "steps": 2, "properly": 2, "(such": 3, "pregnant)": 1, "invalidated": 1, "event": 3, "turned": 7, "conceive": 1, "return": 5, "bride-price": 3, "special": 3, "engagement": 1, "notes:": 2, "engagements": 1, "serious": 4, "babylonia": 1, "change": 3, "hammurabi's": 2, "code": 2, "suitor": 3, "changed": 3, "forfeit": 1, "entire": 4, "deposit": 1, "(betrothal": 1, "gift)": 1, "prospective": 1, "father-in-law": 3, "pay": 4, "disappointed": 1, "double": 2, "futhermore": 1, "rival": 2, "persuaded": 2, "wasn't": 5, "allowed": 2, "daughter": 1, "penalties": 3, "acted": 1, "potent": 1, "deterrent": 1, "changes": 1, "powerful": 1, "incentive": 1, "responsible": 1, "incentives": 2, "important": 4, "wish": 2, "comply": 1, "parents'": 1, "wishes": 2, "someone": 3, "`best": 1, "match'": 1, "chosen": 3, "parents": 4, "poem": 2, "featuring": 1, "goddess": 2, "inanna": 5, "known": 2, "penchant": 2, "`free": 1, "love'": 1, "pleased": 2, "lover": 2, "dumuzi": 5, "problems": 1, "guiding": 2, "particular": 1, "proper": 1, "conduct": 1, "resulting": 1, "happy": 4, "religious": 1, "secular": 1, "literature": 2, "doubtful": 1, "interpreted": 1, "have)": 1, "jean": 1, "bottero": 8, "work": 3, "pointing": 1, "how": 22, "encouraged": 1, "successful": 1, "farmer": 1, "god": 2, "enkimdu": 1, "shepherd": 1, "elaborates:": 1, "furtively": 1, "left": 8, "amorous": 1, "teenager": 1, "go": 23, "meet": 1, "beloved": 1, "beneath": 9, "stars": 6, "`which": 1, "sparkled": 1, "did'": 1, "dally": 1, "caresses": 1, "suddenly": 2, "advance": 1, "explain": 1, "absence": 1, "lateness": 1, "mother:": 1, "`let": 1, "me": 11, "/what": 2, "lie": 2, "shall": 2, "tell": 10, "ningal'": 1, "suggests": 1, "answer:": 1, "say": 9, "companions": 1, "listen": 1, "music": 1, "dance": 2, "supposed": 2, "keep": 8, "desired": 2, "path": 1, "toward": 8, "prevent": 1, "engaging": 1, "romances": 1, "produce": 3, "aspect": 1, "one's": 1, "none": 1, "embarrassment": 1, "shyness": 1, "taboo": 1, "mesopotamians'": 1, "\u201chomosexual": 1, "enjoyed\u201d": 1, "fear": 2, "stigma": 3, "mention": 1, "\u201cpreferring": 1, "female": 1, "role\u201d": 1, "writes": 4, "\u201cvarious": 1, "unusual": 1, "positions": 1, "adopted:": 1, "`standing'": 1, "`on": 2, "chair'": 1, "`across": 1, "partner'": 1, "behind'": 1, "`sodomising": 1, "her'": 1, "sodomy": 1, "defined": 3, "anal": 1, "form": 4, "contraceptive": 1, "(101)": 1, "happen": 1, "eccentric": 1, "chosen\u2026instead": 1, "keeping": 1, "favourite": 1, "head": 15, "`make": 1, "roof-terrace": 1, "house'": 1, "threshold": 1, "door'": 1, "`right": 1, "middle": 3, "field": 1, "orchard'": 1, "`in": 2, "deserted": 3, "place'": 1, "`a": 1, "road'": 1, "street'": 1, "either": 4, "whom": 2, "`pounced'": 1, "prostitute": 2, "activity": 1, "culturally": 1, "ennobled": 1, "food": 3, "elevated": 1, "cuisine": 1, "why": 2, "earth": 3, "demeaned": 1, "diminished": 3, "guilty": 1, "gods": 1, "practicing": 1, "third": 4, "harmed": 1, "infringing": 1, "customary": 1, "prohibitions": 1, "controlled": 1, "unfaithful": 1, "spouses": 1, "plenty": 1, "textual": 1, "\u201cwhen": 1, "crimes": 1, "severely": 1, "punished": 1, "judges": 1, "including": 2, "use": 2, "penalty:": 1, "wrong": 3, "secret": 1, "harm": 1, "cohesion": 1, "family\u201d": 1, "(93)": 1, "continues:": 1, "greatly": 1, "consequence": 1, "childlessness": 1, "misfortune": 1, "second": 2, "proved": 2, "infertile": 3, "settled": 3, "status": 1, "jurisprudence": 1, "entirely": 1, "authority": 3, "constraints": 1, "giving": 1, "free": 7, "rein": 1, "although": 4, "monogamy": 1, "whims": 1, "needs": 1, "resources": 1, "add": 3, "`second": 1, "wives'": 1, "concubines": 3, "consulted": 1, "choosing": 1, "responsibility": 1, "sure": 3, "fulfilled": 1, "concubine": 3, "added": 1, "concubine's": 1, "offspring": 1, "inherit": 1, "carry": 2, "name": 5, "primary": 1, "purpose": 2, "afford": 2, "fairly": 1, "ill": 1, "generally": 1, "health": 3, "divorce": 12, "continue": 2, "honor": 2, "upon": 2, "wife's": 6, "position": 1, "home's": 1, "hierarchy": 1, "carried": 3, "inscriptions": 3, "record": 2, "running": 3, "husbands": 1, "caught": 4, "act": 1, "river": 22, "drown": 1, "impaled": 2, "parties": 2, "spared": 1, "\u201cif": 2, "owner": 2, "alive": 1, "king": 3, "equally": 2, "pardon": 1, "lover\u201d": 1, "initiated": 1, "mates": 1, "abuse": 1, "neglect": 2, "seems": 2, "occurred": 1, "male": 1, "blame": 1, "childless": 1, "fault": 1, "ascribed": 1, "grounds": 1, "adultery": 1, "again": 15, "suffer": 2, "situation": 2, "optimal": 1, "little": 9, "`guts'": 1, "knew": 6, "charms": 1, "employing": 1, "guile": 1, "less": 3, "toe": 1, "divinatory": 1, "oracle": 1, "mentions": 3, "ceaselessly": 1, "implores": 1, "repeating:": 1, "`please": 1, "husband'": 1, "we": 12, "told": 5, "gallivanting": 1, "three\u2026as": 1, "times": 11, "returning": 1, "crestfallen": 1, "abandoning": 1, "uncommon": 1, "written": 5, "traveling": 2, "region": 2, "begin": 4, "unless": 1, "rare": 1, "occur": 1, "option": 1, "unhappy": 2, "disgrace": 1, "public": 2, "favored": 1, "expressed": 1, "desire": 1, "husband's": 1, "penniless": 1, "naked\u201d": 1, "(nemet-nejat": 1, "140)": 1, "household": 1, "supreme": 1, "prove": 1, "conclusively": 1, "failed": 1, "uphold": 1, "obtain": 1, "majority": 1, "myths": 3, "descent": 1, "huluppu": 1, "tree": 7, "ereshkigal": 1, "nergal)": 1, "portray": 1, "flattering": 1, "light": 9, "advantage": 2, "males": 1, "recognized": 1, "land": 1, "businesses": 1, "buy": 5, "sell": 2, "slaves": 1, "initiate": 1, "proceedings": 1, "cites": 1, "mentioned": 4, "contracts)": 1, "show": 7, "sumer": 1, "enjoying": 1, "greater": 2, "freedoms": 2, "empire": 1, "(c": 1, "2334)": 1, "influence": 1, "akkad": 1, "\"if": 1, "regarded": 1, "levels": 1, "inferior": 1, "treated": 2, "nevertheless": 1, "enjoyed": 3, "consideration": 1, "rights": 2, "perhaps": 1, "results": 1, "vestiges": 1, "sumerian": 6, "culture\"": 1, "(126)": 1, "culture": 1, "remained": 1, "prevalent": 1, "allow": 2, "freedom": 1, "escape": 1, "homelife": 1, "travel": 1, "difficulties": 2, "legalities": 2, "grandchildren": 2, "addition": 2, "letters": 4, "paintings": 2, "sculpture": 3, "attest": 2, "genuine": 2, "affection": 2, "zimri-lim": 2, "mari": 2, "shiptu": 2, "touching": 5, "cared": 2, "trusted": 2, "relied": 2, "\u201chappy": 2, "flourished": 2, "proverb": 2, "boasting": 2, "borne": 2, "sons": 2, "still": 23, "ready": 3, "(132)": 2, "statue": 2, "seated": 3, "2700": 2, "thusly:": 2, "elderly": 1, "fused": 1, "single": 3, "piece": 1, "gypsum": 1, "rock": 4, "right": 12, "arm": 6, "wrapped": 2, "shoulder": 4, "hand": 10, "tenderly": 1, "clasping": 1, "large": 2, "straight": 2, "ahead": 2, "aged": 1, "hearts": 1, "remembering": 1, "cruel": 1, "western": 1, "begun": 1, "promise": 1, "badly": 2, "others": 5, "struggle": 1, "endure": 1, "unions": 1, "individuals": 1, "presented": 1, "challenges": 1, "overcame": 1, "succumbed": 1, "editorial": 1, "review": 2, "reviewed": 1, "accuracy": 1, "reliability": 1, "adherence": 1, "standards": 1, "prior": 1, "help": 6, "translate": 1, "author": 1, "freelance": 1, "writer": 1, "part-time": 1, "professor": 1, "philosophy": 2, "marist": 1, "college": 2, "joshua": 1, "j": 1, "greece": 1, "germany": 1, "traveled": 4, "egypt": 1, "taught": 2, "level": 1, "client-side": 2, "script": 26, "program": 2, "accompany": 2, "html": 7, "document": 14, "embedded": 1, "executes": 2, "client's": 1, "machine": 1, "loads": 2, "link": 2, "activated": 1, "html's": 1, "support": 5, "scripts": 16, "independent": 1, "scripting": 17, "offer": 1, "authors": 11, "means": 1, "extend": 2, "documents": 4, "highly": 1, "interactive": 1, "ways": 1, "example:": 1, "evaluated": 2, "modify": 1, "contents": 8, "dynamically": 3, "input": 2, "entered": 1, "fill": 3, "parts": 2, "based": 1, "values": 2, "data": 4, "conforms": 1, "predetermined": 1, "ranges": 1, "mutually": 1, "consistent": 1, "etc": 2, "triggered": 1, "affect": 1, "loading": 1, "unloading": 1, "element": 18, "focus": 1, "mouse": 1, "linked": 1, "controls": 1, "(eg": 2, "buttons)": 1, "graphical": 1, "user": 19, "interface": 1, "elements": 2, "types": 1, "attach": 1, "document:": 1, "loaded": 2, "agent": 9, "appear": 3, "within": 4, "agents": 8, "cannot": 2, "handle": 1, "alternate": 2, "content": 6, "via": 2, "noscript": 3, "attribute": 14, "specifies": 3, "location": 1, "external": 3, "element's": 4, "overrides": 2, "default": 8, "specified": 3, "type": 3, "supply": 1, "value": 5, "deprecated": 2, "identifier": 1, "identifiers": 1, "standard": 2, "favor": 1, "boolean": 1, "provides": 1, "hint": 1, "generate": 2, "\"documentwrite\"": 1, "javascript)": 1, "thus": 2, "parsing": 1, "rendering": 1, "attributes": 1, "elsewhere": 1, "number": 1, "body": 7, "file": 1, "src": 4, "interpret": 2, "uri": 2, "ignore": 2, "retrieve": 2, "note": 1, "charset": 1, "refers": 1, "character": 1, "encoding": 1, "designated": 1, "does": 9, "concern": 1, "engines": 4, "syntax": 1, "depends": 1, "rely": 1, "specific": 1, "explicitly": 1, "declaration": 2, "local": 1, "specifying": 1, "specify": 2, "intrinsic": 1, "incorrect": 2, "incorrectly": 1, "authoring": 1, "tools": 3, "avoid": 1, "instance": 1, "conventions": 1, "referring": 2, "objects": 2, "specification": 1, "define": 1, "mechanism": 1, "refer": 2, "assigned": 1, "observe": 1, "following": 4, "precedence": 2, "rules": 1, "identifying": 1, "element:": 1, "takes": 5, "id": 1, "otherwise": 2, "used": 5, "allows": 1, "rendered": 1, "script-aware": 1, "cases:": 1, "render": 2, "configured": 1, "evaluate": 1, "doesn't": 4, "invoked": 1, "earlier": 1, "created": 1, "don't": 6, "recognize": 2, "languages": 1, "javascript": 1, "vbscript": 1, "tcl": 1, "statements": 1, "enclosed": 2, "sgml": 1, "comment": 2, "smart": 2, "understand": 8, "solution": 1, "short": 8, "magic": 7, "well-told": 1, "tale": 1, "need": 1, "complete": 3, "lot": 5, "incredible": 1, "available": 1, "it\u2019s": 18, "perfect": 1, "spend": 2, "break": 3, "moments": 1, "oven": 1, "last": 2, "minutes": 3, "before": 17, "bedtime": 1, "features": 1, "contemporary": 2, "favorite": 3, "taste": 3, "style": 1, "commit": 1, "longer": 4, "genres": 1, "hunter's": 5, "montana": 4, "woke": 7, "stricken": 2, "hours-old": 1, "ascending": 1, "rose-lit": 1, "cumulus": 1, "houses": 1, "barns": 1, "specks": 1, "snowed-in": 1, "valleys": 1, "scrolling": 1, "country": 4, "below": 3, "december\u2014brown": 1, "black": 4, "hills": 3, "streaked": 1, "snow": 29, "flashes": 1, "iced-over": 1, "lakes": 1, "long": 18, "braids": 1, "gleaming": 1, "bottom": 4, "canyon": 1, "wing": 1, "deepened": 1, "blue": 13, "pure": 1, "bring": 3, "tears": 4, "looked": 12, "dark": 8, "airplane": 1, "descended": 1, "chicago": 3, "galaxy": 2, "electric": 2, "vast": 2, "neighborhoods": 1, "clearer": 1, "plane": 2, "glided": 2, "airport\u2014streetlights": 1, "headlights": 2, "stacks": 2, "buildings": 1, "ice": 14, "rinks": 1, "truck": 20, "turning": 3, "stoplight": 2, "scraps": 1, "atop": 2, "warehouse": 1, "winking": 2, "antennae": 1, "faraway": 1, "finally": 12, "converging": 1, "parallels": 1, "runway": 1, "walked": 5, "airport": 1, "banks": 2, "monitors": 1, "felt": 17, "he'd": 4, "lovely": 1, "dream": 5, "perform": 1, "higher-up": 1, "universities": 1, "apparently": 2, "terminal": 1, "thick": 5, "gray": 1, "hurried": 2, "escorted": 1, "jeep": 1, "kept": 4, "gaze": 1, "car": 9, "forty-five": 1, "passing": 1, "lighted": 1, "architecture": 1, "naked": 3, "suburban": 3, "oaks": 1, "heaps": 1, "ploughed": 1, "gas": 5, "stations": 1, "power": 3, "towers": 1, "telephone": 3, "wires": 1, "\"so": 1, "regularly": 1, "attend": 1, "performances\"": 1, "\"no\"": 5, "\"never": 1, "before\"": 1, "parked": 3, "driveway": 1, "elaborate": 1, "mansion": 1, "square": 1, "balconies": 1, "garages": 1, "huge": 7, "triangular": 1, "windows": 7, "fa\u00e7ade": 1, "sleek": 1, "columns": 1, "domed": 1, "steep": 1, "shale": 1, "roof": 3, "inside": 9, "front": 5, "door": 16, "thirty": 5, "nametags": 1, "laid": 2, "table": 6, "tag": 1, "pinned": 3, "sweater": 1, "silent": 2, "tuxedo": 1, "disappeared": 2, "coat": 4, "granite": 2, "foyer": 1, "backed": 1, "grand": 1, "staircase": 1, "spread": 2, "wide": 4, "tapered": 2, "top": 6, "came": 20, "four": 3, "\"hello": 1, "anne\"": 1, "driven": 3, "\"you": 8, "mr": 21, "dumas\"": 1, "pale": 1, "bony": 1, "weightless": 1, "featherless": 1, "university's": 1, "chancellor": 2, "knotting": 1, "bow": 4, "tie": 2, "laughed": 3, "sadly": 1, "ties": 1, "disapproved": 1, "hunter": 38, "shifted": 2, "aside": 3, "curtain": 1, "peered": 1, "wooden": 2, "deck": 3, "angled": 2, "stepped": 2, "width": 1, "changing": 1, "low": 3, "rail": 1, "beyond": 4, "shadows": 1, "pond": 4, "lay": 5, "encircled": 1, "hedges": 3, "marble": 1, "birdbath": 2, "leafless": 2, "trees\u2014oaks": 1, "maples": 7, "sycamore": 1, "white": 10, "bone": 2, "helicopter": 1, "shuttled": 2, "green": 2, "\"have": 1, "books\"": 1, "asked": 9, "nodded": 1, "\"in": 1, "hunter\"": 1, "\"i": 24, "guide": 1, "hunters\"": 1, "settling": 1, "\"does": 1, "bother": 2, "you\"": 2, "\"what\"": 1, "\"killing": 1, "animals": 2, "mean\"": 1, "watched": 11, "snowflakes": 1, "disappear": 2, "killing": 1, "put": 4, "fingers": 5, "\"it": 2, "me\"": 6, "falls": 6, "winter": 18, "1972": 1, "once\u2014you": 1, "watch": 2, "twin": 2, "curtains": 2, "north": 1, "driving": 5, "cattle": 4, "galloped": 1, "fencelines": 1, "bawling": 1, "trees": 6, "toppled": 1, "barn": 1, "tumbled": 2, "highway": 1, "flung": 3, "thrushes": 1, "screaming": 1, "gorse": 1, "thorns": 2, "grotesque": 1, "attitudes": 1, "magician's": 2, "assistant": 1, "fifteen": 3, "orphan": 1, "story:": 1, "glittery": 3, "red": 7, "dress": 3, "legs": 8, "meeting": 1, "hall": 3, "central": 3, "christian": 2, "church": 3, "walking": 1, "armful": 1, "groceries": 1, "tracks": 6, "drove": 9, "alley": 1, "face": 12, "pressed": 4, "magician": 5, "dirty": 1, "cape": 1, "sagging": 1, "banner": 1, "vespucci": 3, "graceful": 1, "smiling": 1, "wrestler": 1, "held": 4, "buckling": 1, "plywood": 2, "coffin": 3, "painted": 2, "garishly": 1, "bolts": 1, "lightning": 1, "neck": 7, "stuck": 1, "ankles": 2, "beamed": 1, "smiled": 4, "broadly": 1, "locked": 3, "saw": 11, "brought": 7, "noisily": 1, "sawing": 2, "half": 9, "wheeled": 1, "apart": 1, "torso": 1, "smile": 1, "faded": 3, "dimmed": 1, "screamed": 3, "wiggle": 2, "toes": 2, "ordered": 2, "flourishing": 1, "wand": 2, "disembodied": 1, "wiggled": 1, "high-heeled": 1, "pumps": 4, "audience": 1, "squealed": 1, "delight": 1, "pink": 2, "fine-boned": 1, "hanging": 5, "hair": 12, "outstretched": 1, "spotlight": 1, "slashing": 1, "groceries\u2014onions": 1, "sack": 1, "flour\u2014tumbled": 1, "else": 1, "blew": 2, "collar": 1, "drifted": 2, "rejoined": 1, "severed": 1, "halves": 1, "unfastened": 2, "buckles": 1, "fluttered": 2, "whole": 5, "climbed": 2, "curtsied": 1, "glittering": 1, "resurrection": 1, "itself": 4, "storm": 3, "pine": 1, "courthouse": 1, "winked": 1, "streetlight": 2, "ushers": 2, "escorting": 1, "crowd": 4, "flashlights": 1, "slinking": 1, "stage": 2, "twice": 3, "leaned": 2, "dais": 1, "glow": 2, "emergency": 1, "exit": 2, "shook": 3, "\"show's": 1, "over\"": 1, "pickup": 1, "trailed": 1, "van": 1, "blizzard": 1, "fundraiser": 1, "butte": 2, "followed": 3, "missoula": 2, "rushed": 1, "performance": 2, "\"just": 3, "plead": 1, "name\"": 1, "persistence": 1, "yes": 3, "bozeman": 1, "plain": 2, "mary": 19, "roberts": 1, "rhubarb": 3, "hotel": 1, "restaurant": 1, "it\"": 6, "\"the": 2, "dummies": 1, "chest": 4, "dummy": 1, "string\"": 1, "\"is": 1, "follow": 2, "town": 8, "isn't": 1, "real\"": 1, "hunt\"": 1, "\"and": 2, "you're": 1, "hunting\"": 2, "\"it's": 5, "funny\"": 1, "\"you're": 2, "right\"": 2, "funny": 1, "i'm": 4, "asleep\"": 1, "plate": 1, "thrilled": 1, "searched": 1, "ate": 4, "\"but": 2, "bigger": 1, "know\"": 4, "afterward": 2, "eaten": 1, "pieces": 4, "carefully": 1, "spoon": 3, "quiet": 6, "sawed": 3, "tony": 1, "life\"": 1, "you'd": 1, "bitterroot": 3, "diner": 2, "watching": 4, "part:": 1, "hitch": 1, "swallowed": 1, "slid": 3, "cleanly": 1, "lips": 2, "ear": 4, "eighteen": 2, "drive": 1, "cabin": 14, "forty": 4, "miles": 4, "missouri": 4, "east": 1, "smith": 1, "valley": 8, "vinyl": 1, "purse": 1, "skidded": 1, "sheered": 1, "steered": 1, "unploughed": 1, "fishtailing": 1, "didn't": 6, "afraid": 2, "possibility": 2, "sink": 4, "drift": 2, "freeze": 2, "pea": 1, "magician's-assistant": 1, "breath": 4, "plumed": 1, "degrees": 1, "zero": 2, "soon": 7, "snowed": 2, "impassable": 1, "spring": 7, "one-room": 1, "furs": 3, "rifles": 1, "walls": 1, "unbolted": 2, "crawl": 6, "space": 4, "hoard:": 1, "hundred": 4, "smoked": 2, "trout": 7, "plucked": 1, "pheasants": 1, "venison": 1, "quarters": 1, "frozen": 11, "hooks": 1, "\"enough": 1, "scanned": 1, "books": 8, "fireplace\u2014a": 1, "monograph": 1, "grouse": 1, "journals": 1, "upland": 1, "game": 2, "birds": 3, "tome": 1, "titled": 1, "bear": 4, "\"are": 1, "tired\"": 1, "\"would": 1, "something\"": 1, "gave": 4, "snowsuit": 1, "strapped": 2, "pair": 2, "leather": 1, "snowshoes": 2, "grizzly": 2, "bad": 2, "clumsy": 1, "creaking": 1, "wind-scalloped": 1, "nearly": 4, "unbearable": 1, "cold": 2, "denned": 1, "hollow": 3, "cedar": 1, "shorn": 2, "three-fingered": 1, "starlight": 2, "resembled": 1, "skeletal": 1, "thrust": 1, "ghoulish": 1, "visitor": 1, "scrabbling": 2, "underworld": 1, "knelt": 7, "knife": 5, "points": 1, "\"put": 1, "here\"": 3, "whispered": 7, "crystallized": 2, "listened": 1, "face-to-face": 1, "ears": 4, "woodpecker": 1, "holes": 1, "trunk": 3, "minute": 4, "tuning": 1, "drowsy": 1, "sigh": 1, "exhalation": 1, "slumber": 2, "widened": 1, "full": 4, "passed": 3, "\"we": 1, "him\"": 5, "dead": 11, "grizzlies": 3, "hibernators": 1, "twigs": 2, "dens": 2, "they're": 3, "up\"": 1, "dig": 2, "mouth": 6, "bent": 3, "waist": 2, "bailed": 1, "dug": 3, "encountered": 1, "smooth": 1, "icy": 3, "crust": 3, "hole": 3, "base": 1, "gently": 2, "dislodged": 1, "plates": 2, "lifted": 2, "smell": 2, "wet": 1, "dog": 8, "mushrooms": 1, "removed": 2, "leaves": 3, "shaggy": 2, "flank": 1, "patch": 1, "brown": 3, "fur": 2, "\"he's": 1, "back\"": 1, "\"this": 2, "belly": 1, "forelegs": 1, "somewhere\"": 1, "pointed": 3, "higher": 2, "beside": 7, "den": 1, "unblinking": 1, "jaw": 1, "hung": 3, "star": 1, "separated": 1, "melted": 2, "sounded": 2, "loud": 1, "wood": 2, "cedars": 1, "\"hush\"": 1, "hissed": 1, "crazy\"": 1, "tugged": 1, "mitten": 2, "teeth": 2, "reached": 7, "pulled": 6, "footing": 1, "clutching": 3, "horrified": 1, "placed": 3, "spread-fingered": 1, "shag": 1, "bear's": 2, "lowered": 1, "snowy": 1, "soft": 3, "silver": 1, "tips": 2, "brush": 1, "cheeks": 4, "nose": 2, "rib": 2, "flexed": 1, "slightly": 2, "lungs": 3, "blood": 12, "slug": 1, "veins": 1, "dreams\"": 1, "echoed": 2, "poured": 2, "ends": 1, "hollowed": 1, "branches": 1, "\"summer\"": 1, "\"blackberries": 1, "dredging": 1, "flanks": 1, "pebbles\"": 1, "i'd": 2, "liked\"": 1, "built": 2, "fire": 10, "\"to": 1, "arms": 3, "grab": 3, "kiss": 2, "eyes\"": 1, "flames": 1, "cutting": 2, "log": 1, "burning": 2, "bridge": 3, "waited": 3, "somehow": 2, "ended": 1, "imagined": 1, "hunt\u2014like": 1, "waiting": 2, "hours": 6, "wallow": 1, "rifle": 1, "barrel": 1, "pack": 5, "antlered": 1, "bull": 4, "elk": 7, "loom": 1, "herd": 2, "inhale": 1, "scatter": 2, "hill": 2, "opening": 1, "shot": 2, "animal": 3, "exactly": 1, "younger": 3, "force": 1, "stay": 1, "\"stay": 1, "winter\"": 1, "bruce": 3, "jabbing": 1, "drink": 3, "straw": 1, "\"i'm": 2, "athletics\"": 1, "athletic": 1, "department": 1, "that\"": 2, "remember": 2, "coach": 1, "track": 4, "hurdles\"": 1, "president": 3, "o'brien": 3, "corner": 2, "reception": 3, "guests": 4, "o'brien's": 1, "probably": 4, "\"that": 1, "wolves": 10, "hurdlers": 1, "snag": 2, "prints": 1, "leaped": 2, "vanished": 1, "eventually": 2, "they'll": 1, "magic\u2014flying": 1, "jump": 1, "coordinated": 1, "leap\"": 1, "\"huh\"": 1, "wouldn't": 2, "loudly": 1, "coyotes": 9, "onto": 6, "howled": 1, "chimney": 2, "rolled": 5, "sweating": 2, "coughed": 1, "chuckled": 1, "chattering": 1, "yard": 2, "nightmares": 1, "\"last": 1, "wolf": 3, "time\"": 1, "mad": 1, "hunger": 1, "moon\"": 1, "couldn't": 3, "maybe": 10, "december": 2, "warmer": 2, "froze\u2014something": 1, "christmas": 1, "eve": 1, "helena": 2, "figure": 1, "skates": 1, "morning": 5, "head-to-toe": 1, "skate": 1, "hips": 2, "dawn": 2, "skating": 1, "coils": 1, "shoals": 1, "alders": 1, "cottonwoods": 1, "bare": 2, "willows": 1, "showing": 1, "stretches": 1, "darkness": 1, "wind-polished": 1, "bend": 1, "heron": 1, "tried": 4, "hack": 1, "hammering": 1, "beak": 3, "entombing": 1, "scaly": 1, "upright": 1, "wings": 1, "parted": 1, "final": 4, "desperate": 2, "cry": 2, "reeds": 1, "threw": 1, "thousand": 4, "ladybugs": 1, "hibernating": 3, "orange": 3, "ball": 8, "riverbank": 1, "dormant": 1, "frogs": 1, "mud": 1, "pried": 1, "globe": 2, "honeybees": 1, "hive": 1, "slow-buzzing": 1, "stunned": 1, "sudden": 2, "exposure": 1, "tightly": 1, "packed": 1, "queen": 1, "bee": 1, "shimmying": 1, "warmth": 4, "fainted": 1, "lying": 4, "reveries": 1, "scores": 1, "worker": 1, "bees": 3, "fiercely": 1, "vivid:": 1, "bright": 2, "trails": 2, "clutch": 1, "roses": 1, "honey": 1, "tidily": 1, "brimming": 1, "combs": 1, "learned": 2, "foreign": 1, "keen": 1, "sensitivity": 1, "bubbling": 1, "seed": 4, "planted": 1, "ago": 2, "sprouting": 1, "larger": 1, "powerfully": 1, "shake": 1, "recently": 1, "virtual": 1, "mines": 1, "casting": 2, "slow-fading": 1, "strength": 2, "tethers": 1, "mittens": 1, "could:": 1, "bats": 1, "salamanders": 1, "cardinal": 1, "chick": 1, "nest": 2, "warm": 2, "garter": 1, "snakes": 1, "coiled": 1, "eyelids": 2, "sealed": 1, "stilled": 2, "insect": 1, "slumbering": 1, "amphibian": 1, "heaven": 1, "shivering": 1, "crossing": 1, "owls": 1, "quilt": 2, "burrowed": 1, "nestled": 1, "roots": 1, "twilight": 1, "rippling": 1, "auroraswith": 1, "lodged": 1, "splinter": 1, "muds": 1, "gasped": 1, "horse": 2, "demure": 1, "assured": 1, "heel": 1, "struck": 1, "changed\u2014become": 1, "refined": 1, "worse": 1, "wrinkled": 1, "avoiding": 1, "near": 4, "closet": 1, "lunge": 1, "forward": 1, "snatch": 1, "lapels": 1, "wore": 1, "jewelry": 1, "ring": 2, "suit": 2, "double-breasted": 1, "nametag": 2, "lapel": 1, "guest": 1, "courting": 1, "chancellor's": 2, "way\u2014a": 1, "bartender": 1, "tuxedoed": 1, "drinks": 1, "sleeping": 4, "sat": 4, "narrow": 1, "high-backed": 1, "chairs": 1, "recognition": 1, "her\u2014he": 1, "staff": 1, "starched": 1, "whites": 1, "onion": 1, "soup": 1, "scampi": 1, "poached": 1, "salmon": 1, "spoke": 4, "whispers": 1, "blowing": 1, "thawed": 1, "saucers": 1, "stirring": 1, "quickening": 1, "soul": 1, "dawns": 1, "rod": 1, "hurry": 1, "chill": 1, "water": 7, "insects": 3, "ringing": 1, "calls": 4, "clients": 3, "season": 2, "april": 3, "occasional": 1, "client": 6, "wanted": 13, "mountain": 2, "lion": 1, "trip": 1, "late": 1, "summer": 3, "thermos": 1, "pick": 2, "lawyer": 2, "widower": 1, "politician": 1, "cutthroat": 1, "fish": 2, "guts": 1, "eager": 1, "stories\u2014native": 1, "leaping": 1, "fifteen-foot": 1, "cataracts": 1, "stubborn": 1, "wedged": 1, "june": 1, "bored": 1, "lonely": 2, "wandered": 2, "forest": 1, "woods": 1, "dense": 1, "graveyard": 1, "slept": 2, "emerging": 2, "cocoons": 1, "winging": 1, "buzzing": 1, "multiplying": 1, "litters": 1, "gaining": 1, "weight": 4, "cubs": 2, "splashed": 2, "chicks": 1, "worms": 1, "longed": 1, "stillness": 1, "bone-on-bone": 1, "antlers": 1, "september": 1, "big-game": 1, "hunters": 1, "different:": 1, "antelope": 2, "moose": 1, "doe": 2, "wolverine": 1, "shoot": 1, "sandhill": 1, "cranes": 1, "heads": 1, "seven-by-seven": 1, "royal": 1, "bulls": 1, "smelling": 1, "stupid": 1, "texan": 1, "wheezing": 1, "shape": 1, "bloodthirsty": 1, "yorker": 1, "photograph": 1, "bears": 1, "pistol": 1, "boot": 1, "fired": 1, "wildly": 1, "nightly": 1, "scrubbed": 1, "coveralls": 1, "fade": 1, "rust": 1, "basin": 1, "filled": 2, "afternoon": 1, "naps": 1, "skill": 1, "getting": 1, "reassembled": 1, "divining": 1, "robin": 1, "despite": 2, "heat": 4, "noise": 1, "screens": 1, "hornets": 1, "sped": 1, "sun": 7, "urgent": 1, "southern": 2, "autumn": 1, "exhausted": 1, "forearms": 1, "stained": 1, "stripping": 1, "cottonwoods\u2014too": 1, "grip": 1, "forces": 1, "control": 1, "over\u2014the": 1, "october": 1, "revolutions": 1, "remember:": 1, "thanksgiving": 1, "six-foot": 1, "drifts": 2, "phone": 4, "chinook": 1, "terrible": 1, "three-inch": 1, "covered": 1, "ranches": 2, "crashed": 3, "bled": 1, "kicking": 2, "deer": 3, "punched": 1, "tiny": 1, "hooves": 1, "suffocated": 1, "veined": 1, "mornings": 1, "coyote": 3, "inches": 2, "hardwood": 1, "hoard": 1, "floorboards": 3, "reinforced": 1, "baking": 1, "sheets": 2, "nailing": 1, "hinges": 1, "claws": 1, "metal": 2, "charged": 2, "shout": 2, "dying:": 1, "keeling": 1, "emaciated": 1, "clattering": 1, "drunken": 1, "skeleton": 1, "radio": 2, "losses": 1, "dreamt": 3, "soaring": 1, "fences": 1, "tearing": 2, "steaming": 1, "carcasses": 1, "february": 2, "grabbed": 1, "dashed": 1, "barefoot": 1, "numb": 1, "gone": 8, "chewing": 1, "digging": 3, "swung": 1, "arrows": 3, "aluminum": 1, "shafts": 1, "tipped": 1, "broadheads": 1, "squatted": 1, "entrance\u2014their": 1, "exit\u2014with": 1, "draw": 2, "arrow": 2, "nocked": 1, "pad": 1, "quietly": 1, "coughing": 1, "panted": 1, "steadily": 2, "bite": 1, "blocks": 1, "spent": 1, "quiver:": 1, "dozen": 4, "yelps": 1, "speared": 1, "lashed": 2, "ribs": 1, "tails": 1, "skulls": 1, "muscles": 1, "frenzy": 1, "bloomed": 2, "thigh": 2, "otherworldly": 1, "screams": 1, "wounded": 1, "grunts": 3, "curses": 1, "fought": 1, "tunneled": 1, "hell": 2, "pouring": 1, "violence": 1, "send": 1, "souls": 1, "boards": 1, "skyward": 1, "blood-soaked": 2, "hungry": 2, "bitten": 1, "worked": 1, "starve": 1, "lugged": 1, "slate": 1, "bark": 2, "wedge": 1, "tires": 3, "excavated": 1, "engine": 3, "ramped": 1, "wind-crusted": 1, "brief": 1, "wonderful": 2, "moment": 3, "careening": 1, "washing": 1, "spinning": 1, "pistons": 1, "churning": 1, "unspooling": 1, "slowly": 5, "painfully": 1, "hopeless": 1, "hardly": 2, "anywhere": 3, "sheet": 2, "truck's": 2, "revved": 1, "eight-foot": 1, "sank": 1, "weak": 1, "smoky": 1, "cut": 2, "boughs": 1, "trickles": 2, "ran": 3, "froze": 1, "solid": 2, "twisting": 1, "constellations": 1, "farther": 1, "colder": 1, "neither": 3, "fully": 2, "nor": 1, "waking": 1, "lope": 1, "reaches": 1, "slavering": 1, "lean": 1, "die": 2, "managed": 1, "kneel": 1, "turn": 5, "nailed": 1, "scrape": 1, "catatonia": 1, "elbows": 1, "knees": 4, "porch": 5, "sign": 2, "crawl-space": 1, "shreds": 1, "siding": 1, "doorframe": 1, "scattered": 2, "kneeling": 2, "hypothermic": 1, "torpor": 1, "dregs": 1, "energy": 2, "constructed": 1, "mug": 1, "weeping": 1, "near-frozen": 1, "flour": 2, "crackers": 1, "cupboards": 1, "amazing": 1, "things\"": 1, "murmured": 1, "spiders": 1, "geese": 2, "incessantly": 1, "abiding": 1, "daylight": 1, "whenever": 1, "eyesight": 1, "fled": 1, "slow": 1, "nauseating": 1, "streaks": 1, "color": 2, "lanterns": 1, "shoveled": 1, "chopped": 1, "maul": 1, "shivered": 1, "jigging": 1, "dough": 1, "hook": 1, "squirrel": 1, "hare": 2, "famished": 1, "whose": 1, "bones": 1, "cracked": 1, "boiled": 1, "handfuls": 1, "march": 1, "cattails": 1, "peel": 1, "tubers": 1, "scribble": 1, "notebook": 1, "paper": 1, "plummeting": 1, "blankets": 1, "sustenance": 1, "learning": 1, "hidden": 1, "weakness": 1, "deepest": 1, "pit": 1, "stomach": 1, "quieted": 1, "demands": 1, "discoveries": 1, "nineteen": 1, "pounds": 2, "marrying": 1, "cage": 1, "pelvis": 1, "scribbled": 1, "senseless": 1, "clues": 1, "snail:": 1, "sleds": 1, "stones": 1, "rain": 4, "owl:": 1, "fixes": 1, "drops": 2, "horse:": 1, "rides": 1, "plains": 1, "brothers": 1, "temperature": 1, "extra": 2, "battery": 1, "excavation": 1, "slushy": 2, "moonlight": 1, "she'd": 2, "surprise": 1, "heated": 1, "baths": 1, "dressed": 2, "clothes": 2, "hadn't": 1, "worn": 1, "months": 2, "threaded": 1, "twine": 1, "belt": 1, "loops": 1, "trousers": 1, "wheel": 1, "dressing": 1, "streaming": 1, "bought": 3, "food\u2014a": 1, "pizzas": 1, "potatoes": 1, "eggs": 1, "carrots": 1, "wept": 1, "bananas": 1, "parking": 2, "drank": 1, "gallon": 1, "milk": 1, "applied": 1, "card": 1, "borrowed": 1, "hamburgers": 1, "sliding": 1, "\"well": 1, "mary\"": 1, "pie\"": 1, "repaired": 1, "fishing": 2, "ravenous": 1, "appetite": 1, "books\u2014essays": 1, "sorcery": 1, "primers": 1, "magic-working": 1, "conjury": 1, "mail-ordered": 1, "hampshire": 1, "orleans": 1, "italy": 1, "week": 4, "collect": 1, "parcel": 1, "office:": 1, "arcana": 1, "mundi": 1, "seer's": 1, "dictionary": 1, "paragon": 1, "wizardry": 1, "occult": 1, "ancients": 1, "opened": 3, "page": 1, "\"bring": 1, "fillet": 1, "altar": 1, "burn": 1, "fresh": 1, "frankincense": 1, "regained": 1, "dreaming": 1, "brewing": 1, "pages": 1, "steady": 1, "diet": 1, "meat": 1, "vegetables": 1, "shone": 2, "glowed": 2, "supper": 1, "firelight": 1, "blackbird": 1, "feathers": 1, "tied": 1, "heron's": 1, "breasts": 1, "november": 1, "sunday": 1, "cross-country": 1, "skied": 2, "ravens": 1, "shrieked": 2, "palm": 4, "leathered": 1, "skull": 1, "\"there\"": 1, "moaned": 1, "feel\"": 1, "standing": 4, "\"what": 3, "trembling": 1, "flowing": 2, "out\"": 1, "goes": 8, "sees\"": 1, "that's": 1, "impossible\"": 1, "saying": 2, "dream\"": 1, "do\"": 1, "wolves\"": 1, "elk's": 1, "crops": 1, "ravens\"": 1, "ask": 2, "anyone": 1, "clearly": 2, "fine": 2, "wakefulness": 2, "tenuous": 2, "clearest": 1, "newt": 2, "fence": 1, "styx": 1, "area": 1, "snowfield": 1, "lakes:": 1, "smoke": 4, "night\u2014slick": 1, "glazing": 1, "wheat": 1, "roofs": 1, "dropped": 4, "chains": 1, "rattling": 2, "heading": 1, "fort": 1, "benton": 1, "noon": 1, "marlin": 6, "spokes": 4, "snowplough": 1, "driver": 2, "grade": 1, "school": 2, "plough": 3, "block": 1, "crash": 1, "riverbed": 1, "girders": 1, "sprinting": 1, "jeans": 1, "t-shirt": 2, "water\u2014a": 1, "jeweler": 1, "butcher": 1, "apron": 1, "scrambled": 1, "wading": 1, "rapids": 1, "prying": 1, "cab": 2, "stumbling": 1, "shoulders": 3, "crushed": 1, "hood": 1, "careened": 1, "snow-covered": 1, "slope": 1, "jeweler's": 1, "leg": 3, "butcher's": 1, "marlin's": 3, "ankle": 1, "finger": 1, "her:": 1, "pedaling": 1, "bicycle": 1, "child's": 1, "seat": 6, "mounted": 1, "rear": 1, "tire": 1, "helmeted": 1, "boy\u2014marlin's": 1, "son\u2014strapped": 1, "spangles": 1, "riders": 1, "lane": 2, "giant": 1, "sprawling": 1, "boy": 2, "fist": 1, "storefront": 1, "reflection": 1, "flashed": 1, "vision\u2014like": 1, "ribbon": 1, "rich": 1, "silk\u2014ran": 1, "fluidly": 1, "pedaled": 1, "bike": 1, "boy's": 1, "basements": 1, "everywhere\u2014in": 1, "supermarket": 1, "gasoline": 1, "son": 2, "experts": 1, "\"all": 1, "her\"": 1, "barber": 1, "too\"": 1, "you've": 2, "dreamed\"": 1, "deli": 1, "raved": 1, "pedal": 1, "around\"": 1, "flipped": 1, "idly": 1, "stack": 1, "them\u2014one": 1, "now\"": 2, "portuguese\"": 1, "little\"": 1, "fork": 2, "\"were": 1, "killed\"": 1, "helped": 3, "pull": 3, "good\"": 1, "tricks": 2, "hypnotize": 1, "people\"": 1, "tightened": 1, "furious": 1, "\"why": 1, "can't": 2, "you\u2014\"": 1, "tricks\"": 1, "muttered": 1, "callers": 1, "relentless:": 1, "grieving": 2, "widow": 1, "orphan's": 1, "tribune": 1, "blubbering": 1, "beg": 1, "funeral": 2, "parlor": 1, "insisted": 1, "declared": 1, "moaning": 1, "alive\"": 1, "soaked": 1, "sweat": 2, "\"like": 1, "fizzing": 1, "body\"": 1, "awake": 1, "duck": 1, "exhaustion": 1, "damp": 1, "salmon\"": 1, "\"they": 1, "washed": 3, "shoals\"": 1, "soften": 1, "really": 4, "solace": 1, "good-bye": 1, "ones": 2, "they'd": 1, "no\"": 2, "mean": 2, "palms": 1, "\"as": 1, "you'll": 1, "windshield": 1, "fixed": 2, "leave": 2, "fifty": 2, "hundred\u2014once": 1, "hundred\u2014dollars": 1, "pocket": 3, "weekends": 1, "disappearing": 1, "fearless": 1, "roadkill\u2014a": 1, "crumpled": 1, "porcupine": 1, "shattered": 1, "grille": 1, "husks": 1, "seasons": 1, "drives": 1, "tempted": 1, "thaws": 1, "try": 3, "lose": 1, "rhythm": 1, "pebbles": 1, "downstream": 1, "clacking": 1, "hands\u2014his": 1, "botching": 1, "kills\u2014getting": 1, "upwind": 1, "telling": 1, "unload": 1, "call": 1, "quits": 1, "seconds": 2, "pheasant": 1, "burst": 1, "cover": 2, "pegged": 1, "berated": 1, "careless": 1, "clutched": 1, "bloody": 1, "\"do": 1, "done\"": 1, "\"how": 2, "shaft": 1, "knock": 1, "trot": 1, "resting": 1, "red-faced": 1, "huffing": 1, "\"wolves": 1, "hunt": 1, "\"there": 1, "haven't": 1, "years\"": 1, "money": 4, "boot:": 1, "dollars": 4, "canceled": 1, "stewed": 1, "pacing": 1, "sifting": 1, "rehearsing": 1, "arguments": 1, "sheaf": 1, "bills": 2, "jutting": 1, "shirt": 4, "halfway": 1, "bag": 2, "helping": 1, "good": 4, "afterward\"": 1, "money\"": 1, "desperately": 1, "see\"": 1, "grift": 1, "con\"": 1, "anything:": 1, "talent": 2, "gift\"": 1, "snorted": 1, "\"a": 1, "gift": 1, "hocus-pocus": 1, "swindling": 1, "widows": 1, "savings\"": 1, "lobbed": 1, "hit": 1, "dare": 1, "cried": 1, "frequently": 1, "durations": 1, "visiting": 1, "accident": 2, "sites": 1, "parlors": 1, "ceiling-mounted": 1, "television": 1, "interviewed": 1, "manhattan": 1, "demand": 1, "commune": 2, "dead\"": 1, "interviewer": 2, "peace\"": 1, "well\"": 1, "camera": 1, "bookstore": 1, "animals:": 1, "rampant": 1, "glorious": 1, "buck": 1, "sudan": 1, "backbone": 1, "fossilized": 1, "stegosaur": 1, "wrote": 2, "frustration": 1, "divined": 1, "network": 1, "flew": 1, "kamchatka": 1, "embrace": 1, "mammoth": 1, "air-lifted": 1, "glacier": 1, "luck": 1, "describing": 1, "slogging": 1, "big-footed": 1, "tide": 1, "sea": 3, "grass": 4, "flaring": 1, "handful": 1, "vague": 1, "allusions": 1, "him\u2014a": 1, "brooding": 1, "hovered": 1, "margins": 1, "killer": 1, "fifty-eight": 1, "perceptibly:": 1, "seeking": 1, "loggers": 1, "thinned": 1, "accessible": 1, "stand": 3, "runoff": 1, "logging": 1, "chocolate-brown": 1, "soil": 1, "forests": 1, "pencil": 1, "letter": 1, "federal": 1, "express": 1, "envelope": 1, "response": 1, "embossed": 1, "stationery": 1, "handwriting": 1, "efficient": 1, "ticket": 1, "thank": 2, "sherbet": 1, "candles": 2, "distributed": 1, "room:": 1, "sills": 1, "banister": 1, "mantel": 1, "bookshelves": 1, "bar": 1, "caskets": 4, "carpet": 2, "bit": 1, "lids\u2014they": 1, "outside\u2014was": 1, "melting": 1, "circles": 1, "cushions": 1, "entryway": 1, "uncomfortably": 1, "cradling": 1, "cups": 1, "gulping": 1, "gin": 1, "vodka": 1, "tumblers": 1, "elegant": 1, "motioned": 1, "pinched": 1, "inscrutable": 1, "impression": 1, "leaner": 1, "o'brien\"": 1, "difficult": 1, "blade": 1, "cliff": 1, "hope": 1, "merely": 1, "fog": 2, "peer": 1, "necessarily": 1, "collective": 1, "celebrate": 1, "transition": 1, "others\"": 1, "lids": 1, "\"think\"": 1, "\"think": 2, "resolved": 1, "grips": 1, "back\u2014perhaps": 1, "feeling": 1, "wish\"": 1, "closed": 2, "\"of": 1, "sunny": 1, "together\"": 1, "lulling": 1, "wash": 1, "reaching": 1, "whatever\u2014whoever\u2014lay": 1, "somewhere": 1, "loss": 1, "happening\u2014a": 1, "flitting": 1, "dim": 1, "unsettling": 1, "feather": 1, "brushed": 1, "sides": 2, "wondered": 1, "hypnotizing": 1, "fight": 1, "snap": 1, "poking": 1, "swept": 1, "ceiling": 1, "lightly": 1, "pulsed": 1, "broad": 1, "flat": 1, "glittered": 1, "polished": 1, "dune": 1, "shins": 1, "dunes": 1, "shorebird": 1, "diving": 2, "crabs": 1, "yards": 1, "building": 3, "castles": 1, "sand": 1, "song": 1, "lilting": 1, "reclining": 1, "umbrella": 1, "iced": 1, "tea": 1, "sweet": 1, "bitter": 1, "trace": 1, "mint": 1, "cell": 3, "breathe": 2, "shuttling": 1, "outward": 1, "richly": 1, "dissolving": 1, "paddling": 1, "linen": 1, "gowns": 1, "visible": 1, "people's": 1, "cheeks\u2014o'brien's": 1, "maples's": 1, "bowed": 1, "sudsy": 1, "sinks": 1, "dishes": 1, "rim": 1, "undersides": 1, "clouds": 2, "reflected": 2, "join": 1, "preparing": 1, "say:": 1, "belief": 1, "expression": 1, "gratitude": 1, "providing": 1, "fierce": 1, "unfettered": 1, "surely": 1, "understood": 1, "dashing": 2, "fragile": 1, "bond": 1, "dandelion": 1, "wispy": 1, "sphere": 1, "instead": 2, "fluttering": 1, "melt": 1, "trembled": 1, "trapped": 1, "parallel": 1, "gorgeous": 1, "descriptions": 1, "you\u2019ll": 1, "amazed": 1, "doerr\u2019s": 1, "pulitzer": 1, "prize-winning": 1, "novel": 1, "they\u2019ve": 2, "ok\u2014swell\u2014but": 1, "argue": 4, "argument": 1, "circularity": 1, "ray": 42, "thinks": 12, "greyhounds": 1, "chasing": 1, "mechanical": 1, "rabbit": 2, "scenery": 1, "don\u2019t": 10, "they\u2019d": 1, "kids": 4, "couldn\u2019t": 1, "tested": 1, "that\u2019s": 8, "doctor": 1, "jack": 2, "russell": 1, "biznezz": 1, "spell": 1, "loves": 1, "anyway": 3, "wal-mart": 4, "house\u2014they": 1, "can\u2019t": 9, "it\u2014but": 1, "says": 55, "won\u2019t": 3, "plumbing": 1, "lawn": 1, "bald": 1, "patches": 1, "shanty": 1, "irish": 1, "drought": 1, "tells": 9, "grow": 1, "wait": 4, "we\u2019re": 4, "there\u201d": 1, "we\u2019ll": 2, "bankrupts\u201d": 1, "talks": 2, "biz": 12, "mostly": 1, "think\u201d": 1, "\u201cit\u2019s": 1, "worry": 2, "bankrupt": 1, "forgot\u201d": 1, "castle": 3, "pretty": 2, "\u201cthe": 1, "economy\u201d": 1, "maine": 1, "janitor": 1, "joke": 1, "penny": 1, "wise": 1, "pound": 2, "foolish\u201d": 1, "\u201cyou": 3, "you\u201d": 1, "rearview": 4, "hates": 3, "occurs": 2, "knows": 12, "quik-pik\u201d": 1, "kickball": 5, "tallie\u2019s": 1, "birthday\u201d": 1, "tallie": 3, "brother\u2019s": 1, "supposes": 1, "niece": 2, "he\u2019s": 13, "mary\u2019s": 6, "balls": 2, "wal-mart\u201d": 2, "\u201cand": 2, "everything\u2019s": 1, "cheaper": 2, "wally": 1, "world\u201d": 1, "quik-pik": 5, "purple": 8, "there\u2019ll": 2, "aren\u2019t": 2, "back\u201d": 2, "pressing": 1, "she\u2019ll": 4, "football": 1, "quarterbacking": 1, "underdog": 1, "team": 1, "spots": 1, "passes": 1, "it\u2019ll": 1, "says\u2014as": 1, "torrent": 1, "traffic": 1, "rolling": 2, "stores": 1, "\u201ci\u2019ll": 2, "dash": 2, "ninety-nine": 2, "cents\u201d": 1, "\u201cdon\u2019t": 1, "pinchpenny\u201d": 1, "foolish": 1, "\u201cbuy": 1, "smokes": 6, "quit": 2, "we\u2019d": 1, "saves": 1, "pays": 2, "friend": 1, "carolina": 2, "ship": 1, "cartons": 1, "carton": 1, "doesn\u2019t": 7, "economize": 1, "what\u2019s": 1, "packs": 1, "day\u201d": 1, "\u201cnow": 1, "pack\u201d": 1, "gets": 5, "heavier": 2, "feeds": 1, "damn": 2, "russells": 1, "ought": 3, "indian": 1, "them\u201d": 1, "tax-free": 1, "rez": 1, "years\u201d": 1, "\u201ci\u2019ve": 1, "listen\u201d": 1, "pulls": 3, "parks": 1, "store": 3, "shade": 1, "overhead": 1, "car\u2019s": 1, "air-conditioner": 1, "panting": 1, "grinning": 1, "quit\u201d": 1, "debbies\u201d": 1, "this\u2014he": 1, "sensitive": 1, "weight\u2014but": 1, "mystery": 1, "more\u201d": 1, "\u201cany": 1, "anymore": 1, "shelf": 2, "twenty-four-pack": 1, "snooping\u201d": 1, "flush": 1, "rises": 1, "sees": 7, "good-looking": 2, "everybody": 2, "otherwisei": 1, "bottle": 2, "opener\u201d": 1, "cream": 1, "soda": 1, "old-fashioned": 1, "cap": 1, "goddam": 1, "cupboard": 1, "ball\u201d": 1, "sport": 1, "cheap": 2, "ones\u201d": 1, "\u201cthat": 1, "off-brand": 2, "premium": 2, "harmony": 1, "called\u201d": 1, "homemade": 1, "shit": 1, "shut": 2, "suppose": 1, "i\u2019ll": 4, "cents": 3, "poison": 1, "baby": 2, "likes": 2, "boast": 1, "company": 1, "shits": 2, "licks": 1, "twinkies": 1, "it\u201d": 1, "\u201cor": 1, "ho": 1, "hos": 1, "mean\u201d": 1, "slams": 1, "concrete": 1, "cube": 1, "sidle": 3, "she\u2019s": 14, "ell": 1, "buddy": 1, "lies": 1, "closes": 1, "paws": 2, "shuffle": 3, "puts": 4, "(in": 1, "jolly": 1, "voice)": 1, "facing": 1, "sits": 2, "opens": 1, "glove": 1, "compartment": 1, "rat\u2019s": 1, "papers": 1, "cigarettes": 2, "forgotten": 1, "hostess": 1, "sno": 3, "wrapper": 1, "pokes": 1, "stiff": 1, "corpse": 2, "older": 1, "ark": 1, "poison\u201d": 1, "unwraps": 1, "tosses": 1, "\u201cwant": 1, "snarks": 1, "bites": 1, "licking": 1, "bits": 1, "coconut": 1, "pitch": 1, "bitch": 1, "gauge": 1, "roll": 2, "he\u2019d": 1, "bake": 1, "seventy-nine": 1, "yellow": 1, "princess": 1, "\u201cchrist": 1, "pony\u201d": 1, "cool": 1, "vents": 1, "saving": 1, "fuck": 2, "weaken": 1, "remark": 1, "debbies": 1, "jogging": 1, "tits": 1, "forth": 1, "smock": 6, "starts": 3, "cracks": 1, "inch": 1, "blond-haired": 1, "wife\u201d": 1, "puffs": 1, "shines": 1, "something\u2019s": 1, "unconscious": 3, "ghosh": 19, "attack": 2, "911": 1, "locks": 1, "follows": 2, "wire": 4, "cylinder": 3, "kickballs": 3, "\u201chot": 1, "fun": 1, "summertime\u201d": 1, "linoleum": 1, "dark-skinned": 2, "khaki": 1, "pants": 1, "\u201cmr": 2, "manager\u201d": 1, "customers": 2, "seventies": 1, "fat": 7, "fatter": 2, "sir": 3, "lady\u2019s": 1, "husband\u201d": 1, "asks": 4, "yes\u201d": 1, "\u201cyes": 1, "am": 2, "sorry": 2, "dead\u201d": 1, "artificial": 1, "respiration": 1, "mouth-to-mouth": 1, "putting": 1, "french-kissing": 1, "breathing": 2, "kneels": 2, "mary\u201d": 2, "\u201cmary\u201d": 1, "trying": 2, "hears": 1, "skin": 2, "air-conditioning": 2, "\u201cthis": 1, "gentleman": 1, "911\u201d": 1, "bugles": 7, "louder": 1, "apologetically": 1, "\u201cshe": 4, "sick": 1, "healthy": 1, "know\u201d": 3, "shakes": 3, "down\u201d": 1, "\u201cnot": 2, "chest\u201d": 1, "guess": 1, "rack": 2, "souvenir": 2, "t-shirts": 1, "royalty": 1, "lousy": 1, "tee-shirt\u201d": 1, "\u201cwould": 1, "\u201cgod": 1, "no\u201d": 1, "startled": 1, "doctors\u201d": 1, "teen-agers": 3, "using": 1, "ray\u2019s": 1, "rushes": 1, "flapping": 2, "backward": 2, "jog": 1, "sidewalk": 3, "shimmers": 1, "pulsing": 1, "rap": 1, "bass": 1, "sounds": 1, "stolen": 1, "heartbeat": 2, "where\u2019s": 1, "ambulance\u201d": 1, "\u201chow": 1, "hurts": 1, "hurt": 1, "he\u2019ll": 1, "spectator": 1, "ambulance": 1, "chevy": 1, "stripes": 1, "jackpot": 1, "flashing": 3, "\u201ccastle": 1, "county": 2, "rescue\u201d": 1, "printed": 1, "waiters": 1, "pushes": 1, "oxygen": 2, "tank": 2, "dolly": 1, "american-flag": 1, "decal": 1, "\u201csorry\u201d": 1, "\u201cjust": 1, "cleared": 1, "oxford\u201d": 1, "\u201caw": 1, "gee\u201d": 1, "\u201cis": 2, "alive\u201d": 1, "damage": 1, "wants": 1, "crying": 2, "played": 1, "cards": 1, "toss": 1, "mercy": 1, "react": 1, "ophthalmoscope": 1, "emt": 8, "listens": 1, "nonexistent": 2, "pressure": 1, "friends": 1, "guesses": 1, "bugs": 1, "returns": 1, "emts": 4, "god\u201d": 2, "lady": 1, "crosses": 1, "oh\u201d": 1, "stands": 1, "crack": 1, "\u201cthey": 1, "offers": 1, "anyone\u2019s": 1, "yanks": 1, "gurney": 2, "rescue": 1, "vehicle": 1, "flip": 1, "fold": 1, "thinning": 2, "holds": 3, "deathbed": 1, "whoo": 1, "hot\u201d": 1, "wiping": 1, "forehead": 1, "sir\u201d": 2, "watches": 1, "lift": 1, "tucked": 2, "retreated": 1, "unrelieved": 1, "sunshine": 1, "stored": 1, "clipboard": 2, "twenty-five": 1, "questions": 1, "answer": 1, "thirty-five": 2, "st": 2, "stevie\u2019s\u201d": 1, "\u201cwhat": 1, "autopsy": 1, "gives": 2, "gasp": 1, "wonders": 1, "fucking": 1, "hopes": 1, "ghosh\u2019s": 2, "decision\u201d": 1, "\u201cbut": 1, "unattended": 1, "say\u201d": 1, "interjects": 1, "mortuary": 3, "hour": 1, "mortuary\u201d": 1, "burial": 1, "plot": 1, "exchange": 1, "burkett": 1, "stevie\u2019s": 1, "wagon": 1, "siren": 1, "countergirl": 1, "celebrity": 1, "niece\u201d": 1, "\u201cshe\u2019s": 1, "birthday": 1, "talia": 1, "actress": 1, "\u201con": 1, "house\u201d": 1, "solemn": 1, "bursts": 1, "\u201cmary": 1, "sodas": 2, "cooler": 1, "prize": 1, "fair": 1, "\u201902": 1, "\u201903": 1, "sad\u201d": 1, "sleep\u201d": 1, "sofa": 2, "thirty-seven": 1, "i\u2019d": 1, "lord": 1, "laying": 1, "runs": 1, "waits": 2, "cheek": 1, "\u201cyou\u2019re": 1, "biz\u201d": 1, "clogged": 1, "relief": 1, "\u201cpoor": 1, "forgot": 1, "harmonys": 1, "generosity": 1, "stretch": 1, "hospital": 1, "let's": 1, "click": 1, "spelling": 2, "grammar": 2, "button": 1, "proofing": 3, "tab": 1, "receive": 1, "messages": 1, "installed": 1, "reinstalling": 1}